alumath_Group1/__init__.py
alumath_Group1/matrix_multiplication.py
alumath_Group1-0.1.0.dist-info/METADATA
alumath_Group1-0.1.0.dist-info/WHEEL
alumath_Group1-0.1.0.dist-info/top_level.txt
alumath_Group1-0.1.0.dist-info/RECORD
