Metadata-Version: 2.1
Name: alumath-Group1
Version: 0.1.0
Summary: A Python library for advanced matrix operations, including multiplication.
Home-page: https://github.com/Flo-renc/ML_peer_group_1_F-A.git
Author: Peer_Group1
Author-email: d.ganza@alustudent.com
Classifier: Programming Language :: Python :: 3
Classifier: License :: OSI Approved :: MIT License
Classifier: Operating System :: OS Independent
Classifier: Topic :: Scientific/Engineering :: Mathematics
Classifier: Topic :: Software Development :: Libraries :: Python Modules
Requires-Python: >=3.6
